{"searchDocs":[{"title":"Introduction","type":0,"sectionRef":"#","url":"/simple-web-programming/docs/intro","content":"","keywords":"","version":"Next"},{"title":"Getting Started​","type":1,"pageTitle":"Introduction","url":"/simple-web-programming/docs/intro#getting-started","content":" If you need customizing or help, contact Seon Woo Kim. ","version":"Next","tagName":"h2"},{"title":"Markdown Features Example","type":0,"sectionRef":"#","url":"/simple-web-programming/docs/second/example","content":"","keywords":"","version":"Next"},{"title":"Headings​","type":1,"pageTitle":"Markdown Features Example","url":"/simple-web-programming/docs/second/example#headings","content":" H1 Heading  ","version":"Next","tagName":"h2"},{"title":"H2 Heading​","type":1,"pageTitle":"Markdown Features Example","url":"/simple-web-programming/docs/second/example#h2-heading","content":" ","version":"Next","tagName":"h2"},{"title":"H3 Heading​","type":1,"pageTitle":"Markdown Features Example","url":"/simple-web-programming/docs/second/example#h3-heading","content":" H4 Heading​  H5 Heading​  H6 Heading​  ","version":"Next","tagName":"h3"},{"title":"Emphasis​","type":1,"pageTitle":"Markdown Features Example","url":"/simple-web-programming/docs/second/example#emphasis","content":" Italic text or Italic text  Bold text or Bold text  Bold and Italic text or Bold and Italic text  ","version":"Next","tagName":"h2"},{"title":"Lists​","type":1,"pageTitle":"Markdown Features Example","url":"/simple-web-programming/docs/second/example#lists","content":" ","version":"Next","tagName":"h2"},{"title":"Unordered List​","type":1,"pageTitle":"Markdown Features Example","url":"/simple-web-programming/docs/second/example#unordered-list","content":" Item 1 Subitem 1Subitem 2 Item 2Item 3  ","version":"Next","tagName":"h3"},{"title":"Ordered List​","type":1,"pageTitle":"Markdown Features Example","url":"/simple-web-programming/docs/second/example#ordered-list","content":" First itemSecond item Subitem 1Subitem 2 Third item  ","version":"Next","tagName":"h3"},{"title":"Links​","type":1,"pageTitle":"Markdown Features Example","url":"/simple-web-programming/docs/second/example#links","content":" GitHub  ","version":"Next","tagName":"h2"},{"title":"Images​","type":1,"pageTitle":"Markdown Features Example","url":"/simple-web-programming/docs/second/example#images","content":"   ","version":"Next","tagName":"h2"},{"title":"Blockquotes​","type":1,"pageTitle":"Markdown Features Example","url":"/simple-web-programming/docs/second/example#blockquotes","content":" This is a blockquote.  ","version":"Next","tagName":"h2"},{"title":"Code​","type":1,"pageTitle":"Markdown Features Example","url":"/simple-web-programming/docs/second/example#code","content":" ","version":"Next","tagName":"h2"},{"title":"Inline Code​","type":1,"pageTitle":"Markdown Features Example","url":"/simple-web-programming/docs/second/example#inline-code","content":" Here is some inline code.  ","version":"Next","tagName":"h3"},{"title":"Code Block​","type":1,"pageTitle":"Markdown Features Example","url":"/simple-web-programming/docs/second/example#code-block","content":" console.log('Hello, world!');   ","version":"Next","tagName":"h3"},{"title":"Tables​","type":1,"pageTitle":"Markdown Features Example","url":"/simple-web-programming/docs/second/example#tables","content":" Header 1\tHeader 2\tHeader 3Row 1\tData 1\tData 2 Row 2\tData 3\tData 4  ","version":"Next","tagName":"h2"},{"title":"Horizontal Rule​","type":1,"pageTitle":"Markdown Features Example","url":"/simple-web-programming/docs/second/example#horizontal-rule","content":"   ","version":"Next","tagName":"h2"},{"title":"Task Lists​","type":1,"pageTitle":"Markdown Features Example","url":"/simple-web-programming/docs/second/example#task-lists","content":"  Task 1 Task 2 Task 3  ","version":"Next","tagName":"h2"},{"title":"Strikethrough​","type":1,"pageTitle":"Markdown Features Example","url":"/simple-web-programming/docs/second/example#strikethrough","content":" This text is strikethrough.  ","version":"Next","tagName":"h2"},{"title":"Emoji​","type":1,"pageTitle":"Markdown Features Example","url":"/simple-web-programming/docs/second/example#emoji","content":" Here is a smiley face emoji: 😄  ","version":"Next","tagName":"h2"},{"title":"HTML​","type":1,"pageTitle":"Markdown Features Example","url":"/simple-web-programming/docs/second/example#html","content":" This is a paragraph in HTML. ","version":"Next","tagName":"h2"},{"title":"Markdown Features Example","type":0,"sectionRef":"#","url":"/simple-web-programming/docs/first/example","content":"","keywords":"","version":"Next"},{"title":"Headings​","type":1,"pageTitle":"Markdown Features Example","url":"/simple-web-programming/docs/first/example#headings","content":" H1 Heading  ","version":"Next","tagName":"h2"},{"title":"H2 Heading​","type":1,"pageTitle":"Markdown Features Example","url":"/simple-web-programming/docs/first/example#h2-heading","content":" ","version":"Next","tagName":"h2"},{"title":"H3 Heading​","type":1,"pageTitle":"Markdown Features Example","url":"/simple-web-programming/docs/first/example#h3-heading","content":" H4 Heading​  H5 Heading​  H6 Heading​  ","version":"Next","tagName":"h3"},{"title":"Emphasis​","type":1,"pageTitle":"Markdown Features Example","url":"/simple-web-programming/docs/first/example#emphasis","content":" Italic text or Italic text  Bold text or Bold text  Bold and Italic text or Bold and Italic text  ","version":"Next","tagName":"h2"},{"title":"Lists​","type":1,"pageTitle":"Markdown Features Example","url":"/simple-web-programming/docs/first/example#lists","content":" ","version":"Next","tagName":"h2"},{"title":"Unordered List​","type":1,"pageTitle":"Markdown Features Example","url":"/simple-web-programming/docs/first/example#unordered-list","content":" Item 1 Subitem 1Subitem 2 Item 2Item 3  ","version":"Next","tagName":"h3"},{"title":"Ordered List​","type":1,"pageTitle":"Markdown Features Example","url":"/simple-web-programming/docs/first/example#ordered-list","content":" First itemSecond item Subitem 1Subitem 2 Third item  ","version":"Next","tagName":"h3"},{"title":"Links​","type":1,"pageTitle":"Markdown Features Example","url":"/simple-web-programming/docs/first/example#links","content":" GitHub  ","version":"Next","tagName":"h2"},{"title":"Images​","type":1,"pageTitle":"Markdown Features Example","url":"/simple-web-programming/docs/first/example#images","content":"   ","version":"Next","tagName":"h2"},{"title":"Blockquotes​","type":1,"pageTitle":"Markdown Features Example","url":"/simple-web-programming/docs/first/example#blockquotes","content":" This is a blockquote.  ","version":"Next","tagName":"h2"},{"title":"Code​","type":1,"pageTitle":"Markdown Features Example","url":"/simple-web-programming/docs/first/example#code","content":" ","version":"Next","tagName":"h2"},{"title":"Inline Code​","type":1,"pageTitle":"Markdown Features Example","url":"/simple-web-programming/docs/first/example#inline-code","content":" Here is some inline code.  ","version":"Next","tagName":"h3"},{"title":"Code Block​","type":1,"pageTitle":"Markdown Features Example","url":"/simple-web-programming/docs/first/example#code-block","content":" console.log('Hello, world!');   ","version":"Next","tagName":"h3"},{"title":"Tables​","type":1,"pageTitle":"Markdown Features Example","url":"/simple-web-programming/docs/first/example#tables","content":" Header 1\tHeader 2\tHeader 3Row 1\tData 1\tData 2 Row 2\tData 3\tData 4  ","version":"Next","tagName":"h2"},{"title":"Horizontal Rule​","type":1,"pageTitle":"Markdown Features Example","url":"/simple-web-programming/docs/first/example#horizontal-rule","content":"   ","version":"Next","tagName":"h2"},{"title":"Task Lists​","type":1,"pageTitle":"Markdown Features Example","url":"/simple-web-programming/docs/first/example#task-lists","content":"  Task 1 Task 2 Task 3  ","version":"Next","tagName":"h2"},{"title":"Strikethrough​","type":1,"pageTitle":"Markdown Features Example","url":"/simple-web-programming/docs/first/example#strikethrough","content":" This text is strikethrough.  ","version":"Next","tagName":"h2"},{"title":"Emoji​","type":1,"pageTitle":"Markdown Features Example","url":"/simple-web-programming/docs/first/example#emoji","content":" Here is a smiley face emoji: 😄  ","version":"Next","tagName":"h2"},{"title":"HTML​","type":1,"pageTitle":"Markdown Features Example","url":"/simple-web-programming/docs/first/example#html","content":" This is a paragraph in HTML. ","version":"Next","tagName":"h2"}],"options":{"id":"default"}}